karrio/mappers/easyship/__init__.py
karrio/mappers/easyship/mapper.py
karrio/mappers/easyship/proxy.py
karrio/mappers/easyship/settings.py
karrio/plugins/easyship/__init__.py
karrio/providers/easyship/__init__.py
karrio/providers/easyship/error.py
karrio/providers/easyship/manifest.py
karrio/providers/easyship/metadata.json
karrio/providers/easyship/rate.py
karrio/providers/easyship/tracking.py
karrio/providers/easyship/units.py
karrio/providers/easyship/utils.py
karrio/providers/easyship/pickup/__init__.py
karrio/providers/easyship/pickup/cancel.py
karrio/providers/easyship/pickup/create.py
karrio/providers/easyship/pickup/update.py
karrio/providers/easyship/shipment/__init__.py
karrio/providers/easyship/shipment/cancel.py
karrio/providers/easyship/shipment/create.py
karrio/schemas/easyship/__init__.py
karrio/schemas/easyship/error_response.py
karrio/schemas/easyship/manifest_request.py
karrio/schemas/easyship/manifest_response.py
karrio/schemas/easyship/pickup_cancel_response.py
karrio/schemas/easyship/pickup_request.py
karrio/schemas/easyship/pickup_response.py
karrio/schemas/easyship/rate_request.py
karrio/schemas/easyship/rate_response.py
karrio/schemas/easyship/shipment_cancel_response.py
karrio/schemas/easyship/shipment_request.py
karrio/schemas/easyship/shipment_response.py
karrio/schemas/easyship/tracking_request.py
karrio/schemas/easyship/tracking_response.py
karrio_easyship-2026.1.4.dist-info/METADATA
karrio_easyship-2026.1.4.dist-info/WHEEL
karrio_easyship-2026.1.4.dist-info/entry_points.txt
karrio_easyship-2026.1.4.dist-info/top_level.txt
karrio_easyship-2026.1.4.dist-info/RECORD
